Workbook

Sheet 凡例
A1: 生活介護事業所 収支計画モデル v2(広島市・定員20名想定)
A3: 改訂について(v2)
A4: ・本v2は、障害福祉の経営者および広島市指定更新担当職員を想定した2種類の専門家レビューを反映した改訂版です。
A5: ・主な修正：看護職員を必置の独立職種として配置／機能訓練指導員(PT・OT)を追加／面積・賃料・内装費を実勢水準に是正／送迎加算・処遇改善加算の単価を最新の公表値に修正(処遇改善加算は収入と同額を人件費側にも計上し損益中立化)／人員配置比率の分母を前年度平均利用者数(新規は定員×90%)に修正／資金調達計画表と月次資金繰り(Year1)を新設。
A6: ・「前提条件」シートの青字セルが入力用です。黄色背景は特に重要な仮定(要確認)です。広島市への事前相談・最新の報酬告示・現地見積りで必ず確認してください。
A7: ・シート構成：前提条件／報酬単価表(参考)／初期投資／人件費／資金調達計画／資金調達(会長借入)／月次資金繰り(Year1)／収支計画5年
A8: ・本モデルはあくまで計画段階の概算です。数値の一次情報での確認、および税理士・社会保険労務士・建築士・行政書士等の専門家レビューを強く推奨します。

Sheet 報酬単価表
A1: 生活介護 基本報酬単位数(定員20人以下・7時間以上/日)【令和6年度報酬改定】
A2: 平均障害支援区分 | B2: 基本単位数(単位/日) | C2: 生活支援員等 配置比率(対利用者数)
A3: 2 | B3: 546 | C3: 6
A4: 3 | B4: 599 | C4: 6
A5: 4 | B5: 669 | C5: 5
A6: 5 | B6: 964 | C6: 3
A7: 6 | B7: 1288 | C7: 3
A9: 出典・注記：サービス提供時間が9:30〜16:45(7時間15分)など「7時間以上8時間未満」区分に該当することを前提とした単位数です。開所時間を変更する場合は時間区分が変わり単位数も変動するため、厚生労働省告示および広島市提示の最新単価表で必ず再確認してください。区分2以下は546単位として簡易的に一本化しています。

Sheet 初期投資
A1: 初期投資(開設資金)概算 ― ケースA:居抜き物件を優先活用する前提(推奨)
A2: 面積を250〜350㎡(定員20名の実務標準)に是正。用途変更確認申請(200㎡超は原則必要。ただし類似用途間の転用は不要となる余地あり)・消防用設備工事費を追加。什器・車両・改修工事等の設備投資には消費税の仕入税額控除ができない(障害福祉サービスは非課税売上のため)ため、下記の物件取得費〜予備費は本体価格(税抜)で計上し、消費税は別行(控除対象外消費税)でまとめて加算する(税込金額に重ねて課税しないよう、二重計上に注意)。
A3: 項目 | B3: 想定額(税抜) | C3: レンジ(参考) | D3: 備考
A4: 物件取得費(保証金・仲介手数料等) | B4: 4000000 | C4: 300万〜500万円 | D4: 賃貸物件(延床250〜350㎡)を想定。保証金は賃料の6〜10か月分が目安
A5: 内装・バリアフリー改修工事費 | B5: 8000000 | C5: 500万〜1,000万円(居抜き) / 1,800万〜2,700万円(一般物件) | D5: 元デイサービス・クリニック等の居抜き物件を優先探索する前提(ケースB:一般物件の場合は右記上振れ)
A6: 用途変更確認申請・設計費 | B6: 1000000 | C6: 50万〜150万円 | D6: 延床200㎡超は建築基準法上の用途変更確認申請が必須(国交省通知)。建築士への事前確認が前提
A7: 消防用設備工事費 | B7: 1000000 | C7: 居抜きで既存設備流用なら圧縮可、新設なら200万円超も | D7: 消防法施行令別表第一(6)項ハ相当。自動火災報知設備・誘導灯等。消防署予防課への事前相談必須
A8: 什器・備品費 | B8: 2500000 | C8: 150万〜350万円 | D8: 机・椅子・収納・厨房設備・送迎用備品等
A9: 送迎車両(福祉車両2台・購入) | B9: 6000000 | C9: 400万〜800万円 | D9: 新車/中古で幅あり。維持費(燃料・保険等)は別途「前提条件」で計上
A10: 開業前人件費・採用費・研修費 | B10: 4000000 | C10: 300万〜500万円 | D10: 生活支援員等5〜6名の採用費(人材紹介利用時は年収の20〜30%/人)＋開所前研修期間の給与
A11: 法人設立費用 | B11: 300000 | C11: 20万〜30万円 | D11: 登録免許税・司法書士報酬等
A12: 予備費 | B12: 2000000 | C12: 150万〜250万円
A13: 控除対象外消費税(上記設備投資分の概算10%) | B13: =(B5+B6+B7+B8+B9)*0.1 -> 1850000 | D13: 障害福祉サービス(生活介護)の介護給付費収入は非課税売上のため、設備投資に係る消費税は仕入税額控除できず、原則取得価額に算入(税務は税理士に要確認)
A14: 運転資金(Year1の資金繰り実測に基づく最低限必要額) | B14: =-'月次資金繰り(Year1)'!$B$17 -> 32588702 | D14: 国保連への請求は翌月10日締め、入金は翌々月中旬(約2.5か月ラグ)。契約者数を月次で積み上げるYear1の実際の資金繰りを『月次資金繰り(Year1)』シートでシミュレーションし、その最低累積収支(資金が最も枯渇する月の額)を根拠とする。単純な『6か月分』の目安より精度が高い。
A15: 初期投資合計(運転資金込) | B15: =SUM(B4:B14) -> 63238702
A16: (内訳)減価償却対象額 = 内装＋用途変更＋消防設備＋什器＋車両 | B16: =B5+B6+B7+B8+B9 -> 18500000

Sheet 前提条件
A1: 前提条件(青字セル＝入力／黄色背景＝要確認の重要仮定)
A2: 項目 | B2: 値 | C2: 単位・備考
A3: 利用定員 | B3: 20 | C3: 名
A4: 想定する平均障害支援区分(2〜6の整数) | B4: 5 | C4: 『重度対応も積極的に受け入れる』という理念と収支の両立を図るため、区分5(3:1配置)を基本ケースとする。区分を変えると単位数・配置比率が自動で切り替わる。
A5: 基本報酬単位数(自動計算) | B5: =INDEX(報酬単価表!$B$3:$B$7,MATCH(B4,報酬単価表!$A$3:$A$7,0)) -> 964 | C5: 単位/日(7時間以上8時間未満区分)
A6: 生活支援員等 配置比率(自動計算) | B6: =INDEX(報酬単価表!$C$3:$C$7,MATCH(B4,報酬単価表!$A$3:$A$7,0)) -> 3 | C6: 対利用者数
A7: 配置基準の分母(新規指定時：定員×90%) | B7: =B3*0.9 -> 18 | C7: 名。配置比率の分母は前年度平均利用者数が原則だが、新規指定時は実績がないため定員の90%とみなす
A8: 生活支援員等 必要人数(常勤換算・自動計算) | B8: =ROUNDUP(B7/B6,0) -> 6 | C8: 名(端数は非常勤の組み合わせで充当可)
A9: 単位単価 | B9: 10.55 | C9: 円/単位。広島市5級地(上乗せ10%)×通所系サービスの人件費割合(55%)=実質5.5%上乗せの概算値(改訂前は45%=施設系の割合を誤用していたため55%=通所系に是正)。正式な地域区分・人件費割合は広島市提示の単価表で必ず確認。
A10: 送迎加算(Ⅰ)単位数(片道) | B10: 21 | C10: 単位/回。要件：①1回の送迎で平均定員の50%以上(定員20名未満の事業所)が利用、②週3回以上実施
A11: 送迎重度加算 適用(1=適用/0=非適用) | B11: 1 | C11: 送迎利用者のうち区分5・6該当者が60%以上の場合、片道+28単位。本計画は区分5中心のため適用を想定(要件充足を要確認)
A12: 送迎重度加算単位数(片道) | B12: 28 | C12: 単位/回(上記要件を満たす場合)
A13: 送迎利用率 | B13: 0.8 | C13: %(送迎を利用する利用者の割合)
A14: 処遇改善加算(生活介護 フル取得ケース) | B14: 0.084 | C14: 基本報酬に対する割合。旧制度(〜R6.5)の生活介護 加算Ⅰ(4.4%)＋特定処遇改善加算Ⅰ(1.4%)＋ベースアップ等支援加算(2.6%)を全て満額取得した場合の合計値。令和6年6月に一本化された新加算では加算率がさらに引き上げられているとされるため、この8.4%は保守的な下限目安。要件(キャリアパス要件Ⅰ〜Ⅲ、月額賃金改善要件、職場環境等要件)を満たす賃金制度・研修体系の整備が前提。加算額は全額を職員の賃金改善に充てる義務があるため、収支計画では同額を人件費側にも計上し損益に中立化している。
A15: 福祉専門職員配置等加算単位数(Ⅰ+Ⅲ併給) | B15: 21 | C15: 単位/日。生活支援員等のうち社会福祉士・介護福祉士・精神保健福祉士・公認心理師の有資格者が35%以上(Ⅰ:15単位)、かつ常勤75%以上または常勤で3年以上勤続者30%以上(Ⅲ:6単位)を満たす場合。生活介護はⅠ(またはⅡ)とⅢの併給が可能。追加人件費なしで採用方針の工夫のみで取得可能なため、確実性の高い加算として基本ケースに算入。
A16: 入浴実施率(希望者の割合) | B16: 0.5 | C16: %。入浴は希望者のみ週2回を基本とする方針(第3章)
A17: 入浴介助加算 実施回数/週 | B17: 2 | C17: 回
A18: 入浴介助加算単位数 | B18: 40 | C18: 単位/回(要確認)
A19: 食事提供体制加算 対象者割合(低所得者等) | B19: 0.3 | C19: %。経過措置(延長中)。所得要件を満たす利用者のみ対象のため全利用者には適用されない想定
A20: 食事提供体制加算単位数 | B20: 30 | C20: 単位/日(改訂前は96単位としていたが、公表情報では30単位が確認できたため是正)
... A23: 車両関連費(年間、燃料・保険・整備等) | B23: 900000 | C23: 円(福祉車両2台、購入前提)
A24: その他経費(年間、内訳は下記の合計を自動集計) | B24: =SUM(B29:B37) -> 4650000 | C24: 円
A25: 減価償却対象額(初期投資シートより自動計算) | B25: =初期投資!$B$16 -> 18500000 | C25: 円
A26: 減価償却耐用年数(想定・簡便) | B26: 8 | C26: 年(内装・什器・車両で本来は個別だが簡便的に一括。税務は税理士に要確認)
A28: (内訳)その他経費の内訳(年間)
A29: 水道光熱費・消耗品費 | B29: 900000
A30: 給食材料費(外部委託費) | B30: 1500000
A31: 嘱託医費用 | B31: 400000
A32: 税理士顧問料・決算料 | B32: 600000
A33: 社会保険労務士費用 | B33: 200000
A34: 記録・請求システム利用料 | B34: 300000
A35: 損害賠償責任保険・傷害保険 | B35: 250000
A36: 職員健康診断 | B36: 100000
A37: 研修費・広告費・虐待防止/BCP等体制整備費 | B37: 400000
A38: 内訳合計(自動集計。上の『その他経費』セルに反映) | B38: =SUM(B29:B37) -> 4650000

Sheet 人件費
A1: 想定スタッフ体制・年間人件費(常勤換算・法定福利費込)
A2: 看護職員・機能訓練指導員(PT/OT)は生活支援員等と兼務させず、必置の独立職種として配置(人員基準上、生活支援員への兼務は不可)。豊口氏の役員報酬は年度により変動するため、本シートには含めず「収支計画5年」シートで別建て計上。
A3: 職種 | B3: 人数(常勤換算) | C3: 想定年収単価(円/人) | D3: 年間人件費(円) | E3: 備考
A4: 管理者兼サービス管理責任者(丸山氏) | B4: 1 | C4: 4800000 | D4: =B4*C4 -> 4800000 | E4: 常勤・専従が原則。現場の直接支援に恒常的に入る場合はサビ管の専従性・生活支援員等の必要数への算入可否を広島市の事前相談で要確認
A5: 生活支援員等 | B5: =前提条件!$B$8 -> 6 | C5: 3600000 | D5: =B5*C5 -> 21600000 | E5: 配置基準(3:1、定員×90%が分母)に基づく必要人数を自動計算。送迎は本人員のシフト内で輪番対応
A6: 看護職員(看護師・准看護師、必置) | B6: 1 | C6: 4200000 | D6: =B6*C6 -> 4200000 | E6: 生活介護の単位ごとに常勤換算1以上が必置。非常勤の組み合わせ(例:週3日×2名)でも常勤換算1.0を満たす設計可
A7: 機能訓練指導員(PT/OT、非常勤) | B7: 0.4 | C7: 4200000 | D7: =B7*C7 -> 1680000 | E7: 機能訓練を運営規程に位置付ける場合は配置必須。非常勤(週2日程度)を想定。機能訓練体制加算の対象可否は要確認
A8: 事務員(パート) | B8: 0.5 | C8: 3200000 | D8: =B8*C8 -> 1600000 | E8: 経理・請求事務等
A9: 送迎対応 割増手当(固定) | B9: 1 | C9: 600000 | D9: =B9*C9 -> 600000 | E9: 生活支援員等のシフト内での輪番対応を基本とし、早朝・夕方帯の割増手当として計上
A10: 人件費 小計 | D10: =SUM(D4:D9) -> 34480000
A11: 法定福利費等(小計の概算15%) | D11: =D10*0.15 -> 5172000
A12: 人件費 合計(法定福利費込) | D12: =D10+D11 -> 39652000

Sheet 資金調達計画
A1: 資金調達計画(使途と調達を突合)
A2: 使途合計(初期投資シート)に対して、調達合計が上回っているかを必ず確認すること。不足する場合は、居抜き物件へのグレードダウン・自己資金の積み増し・追加融資枠の確保等で埋める。
A4: 【資金使途】
A5: 初期投資合計(Year1資金繰り実測ベースの運転資金込) | B5: =初期投資!$B$15 -> 63238702
A7: 【資金調達】
A8: 調達元 | B8: 金額 | C8: 備考
A9: 自己資金(丸山氏・豊口氏合計、要確定) | B9: 5000000 | C9: 内訳・比率を確定し明記すること(現状仮置き)
A10: 日本政策金融公庫 創業融資(要申込・審査) | B10: 15000000 | C10: 自己資金比率・据置提案・事業計画の説得力次第で変動。複数行への相談を並行
A11: 会長からの借入(シナリオB、要交渉) | B11: 15000000 | C11: 「資金調達(会長借入)」シート参照。金額・金利は未確定
A12: 地方銀行・信用金庫 制度融資(要申込・審査) | B12: 5000000 | C12: 公庫と併用可能な制度融資の活用を検討
A13: 調達合計 | B13: =SUM(B9:B12) -> 40000000
A14: 過不足(調達合計－使途合計。マイナス＝資金ギャップ) | B14: =B13-B5 -> -23238702
A16: ギャップが生じる場合の対応レバー(優先順、経営方針決定〈理念優先〉を反映): ①人員配置体制加算Ⅲの取得(収支計画5年シートに反映済み。Year3以降で発動)に加え、重度障害者支援加算Ⅲ等の取り漏れ加算の追加取得を検討する(人員配置を法定最低ラインへ圧縮するレバーは、理念実現を優先する経営方針により採用しない) ②居抜き物件の徹底活用で内装費を圧縮 ③内装・什器の仕様グレードダウン ④自己資金の積み増し(自己資金比率は融資審査にも直結) ⑤会長借入の増額交渉 ⑥地方銀行・信用金庫の制度融資の追加活用 ⑦多機能型化(生活介護単独の最低定員20名は変更不可のため、定員縮小ではなく他事業との組み合わせで固定費を分散する)
A17: 【5ヵ年累積を踏まえた真の必要資金・ギャップ】(重要)
A18: 設備投資等(初期投資合計－運転資金) | B18: =B5-初期投資!$B$14 -> 30650000
A19: 5ヵ年累積キャッシュフロー不足(収支計画5年シートYear5時点) | B19: =-収支計画5年!$F$37 -> 74001775
A20: 真の必要資金総額 | B20: =B18+B19 -> 104651775
A21: 真の資金ギャップ(調達合計－真の必要資金総額) | B21: =B13-B20 -> -64651775
A22: Year1の運転資金のみを基準にした「過不足」(上記)は約▲2,400万円台だったが、Year2以降も営業赤字・現金流出が続くため、5ヵ年累積で見た真のギャップはこれより大幅に大きい。資金調達・会長への提案は、この「真の資金ギャップ」を基準に検討すること。

Sheet 資金調達(会長借入)
A1: 会長への借入提案・返済シミュレーション(検討中のたたき台)
A2: 青字セルが入力用です。5年間営業赤字が続く新設事業への無担保個人貸付として、年2%は市場水準から見て低すぎる(リスクに見合っていない)との指摘を踏まえ、年3〜5%を基本線としています。借入額・据置期間・返済期間・金利を変更すると返済表が自動再計算されます。実際の条件は会長との相談のうえ決定してください。
A4: シナリオA：開設資金の一部(1,000万円)をお願いする場合
A5: 借入額(無担保想定) | B5: 10000000 | C5: 円
A6: 据置期間(利息のみ支払い) | B6: 1 | C6: 年
A7: 据置後の元金均等返済期間 | B7: 5 | C7: 年
A8: 想定金利(年率) | B8: 0.03 | C8: %。無担保・5年赤字期間ありのリスクを踏まえた水準
A10: 年目 | B10: 期首残高 | C10: 元金返済 | D10: 利息 | E10: 年間支払 | F10: 期末残高
A11: 1 | B11: =$B$5 -> 10000000 | C11: =IF(A11<=$B$6,0,$B$5/$B$7) -> 0 | D11: =B11*$B$8 -> 300000 | E11: =C11+D11 -> 300000 | F11: =B11-C11 -> 10000000
A12: 2 | B12: =F11 -> 10000000 | C12: =IF(A12<=$B$6,0,$B$5/$B$7) -> 2000000 | D12: =B12*$B$8 -> 300000 | E12: =C12+D12 -> 2300000 | F12: =B12-C12 -> 8000000
A13: 3 | B13: =F12 -> 8000000 | C13: =IF(A13<=$B$6,0,$B$5/$B$7) -> 2000000 | D13: =B13*$B$8 -> 240000 | E13: =C13+D13 -> 2240000 | F13: =B13-C13 -> 6000000
A14: 4 | B14: =F13 -> 6000000 | C14: =IF(A14<=$B$6,0,$B$5/$B$7) -> 2000000 | D14: =B14*$B$8 -> 180000 | E14: =C14+D14 -> 2180000 | F14: =B14-C14 -> 4000000
A15: 5 | B15: =F14 -> 4000000 | C15: =IF(A15<=$B$6,0,$B$5/$B$7) -> 2000000 | D15: =B15*$B$8 -> 120000 | E15: =C15+D15 -> 2120000 | F15: =B15-C15 -> 2000000
A16: 6 | B16: =F15 -> 2000000 | C16: =IF(A16<=$B$6,0,$B$5/$B$7) -> 2000000 | D16: =B16*$B$8 -> 60000 | E16: =C16+D16 -> 2060000 | F16: =B16-C16 -> 0
A17: 返済総額 | D17: =SUM(D11:D16) -> 1200000 | E17: =SUM(E11:E16) -> 11200000
A19: シナリオB：開設資金の一部(1,500万円)をお願いする場合
A20: 借入額(無担保想定) | B20: 15000000 | C20: 円
A21: 据置期間(利息のみ支払い) | B21: 1 | C21: 年
A22: 据置後の元金均等返済期間 | B22: 6 | C22: 年
A23: 想定金利(年率) | B23: 0.035 | C23: %。無担保・5年赤字期間ありのリスクを踏まえた水準
A25: 年目 | B25: 期首残高 | C25: 元金返済 | D25: 利息 | E25: 年間支払 | F25: 期末残高
A26: 1 | B26: =$B$20 -> 15000000 | C26: =IF(A26<=$B$21,0,$B$20/$B$22) -> 0 | D26: =B26*$B$23 -> 525000 | E26: =C26+D26 -> 525000 | F26: =B26-C26 -> 15000000
A27: 2 | B27: =F26 -> 15000000 | C27: =IF(A27<=$B$21,0,$B$20/$B$22) -> 2500000 | D27: =B27*$B$23 -> 525000 | E27: =C27+D27 -> 3025000 | F27: =B27-C27 -> 12500000
A28: 3 | B28: =F27 -> 12500000 | C28: =IF(A28<=$B$21,0,$B$20/$B$22) -> 2500000 | D28: =B28*$B$23 -> 437500 | E28: =C28+D28 -> 2937500 | F28: =B28-C28 -> 10000000
A29: 4 | B29: =F28 -> 10000000 | C29: =IF(A29<=$B$21,0,$B$20/$B$22) -> 2500000 | D29: =B29*$B$23 -> 350000 | E29: =C29+D29 -> 2850000 | F29: =B29-C29 -> 7500000
A30: 5 | B30: =F29 -> 7500000 | C30: =IF(A30<=$B$21,0,$B$20/$B$22) -> 2500000 | D30: =B30*$B$23 -> 262500 | E30: =C30+D30 -> 2762500 | F30: =B30-C30 -> 5000000
A31: 6 | B31: =F30 -> 5000000 | C31: =IF(A31<=$B$21,0,$B$20/$B$22) -> 2500000 | D31: =B31*$B$23 -> 175000 | E31: =C31+D31 -> 2675000 | F31: =B31-C31 -> 2500000
A32: 7 | B32: =F31 -> 2500000 | C32: =IF(A32<=$B$21,0,$B$20/$B$22) -> 2500000 | D32: =B32*$B$23 -> 87500 | E32: =C32+D32 -> 2587500 | F32: =B32-C32 -> 0
A33: 返済総額 | D33: =SUM(D26:D32) -> 2362500 | E33: =SUM(E26:E32) -> 17362500
A35: ※資金調達計画表のとおり、これらは開設資金全体(初期投資合計)の一部であり「ほぼ全額」ではない。残りは自己資金・日本政策金融公庫等でまかなう想定。「収支計画5年」シートの営業利益がマイナスの間、この返済額を営業キャッシュフローだけで賄うのは厳しいため、据置期間の延長・返済開始時期の後ろ倒しを早期に相談できる関係性を築いておくこと。無担保・低リスクではない貸付である点を会長にも正直に共有し、条件はリスクに見合う水準で提案する。

Sheet 月次資金繰り(Year1)
A1: 月次資金繰り(開所1年目) ― 契約者数の積み上げ方式
A2: 年次モデル(稼働率60%固定)は開所初日から平均12名が通所する前提となり非現実的なため、契約者数を月次で積み上げるモデルに置き換えた。報酬入金は請求の翌々月中旬(約2.5か月ラグ)であるため、月1・月2はサービス提供があっても入金はゼロ。青字セルが入力用。
A4: 項目 | B4: 月1 | C4: 月2 | D4: 月3 | E4: 月4 | F4: 月5 | G4: 月6 | H4: 月7 | I4: 月8 | J4: 月9 | K4: 月10 | L4: 月11 | M4: 月12
A5: 契約者数(月末、入力) | B5: 3 | C5: 5 | D5: 7 | E5: 9 | F5: 10 | G5: 11 | H5: 12 | I5: 13 | J5: 13 | K5: 14 | L5: 14 | M5: 15
A6: 出席率(想定) | B6: 0.8 | C6: 0.8 | D6: 0.8 | E6: 0.8 | F6: 0.8 | G6: 0.8 | H6: 0.8 | I6: 0.8 | J6: 0.8 | K6: 0.8 | L6: 0.8 | M6: 0.8
A7: 開所日数(月間、概算) | B7: 21 | C7: 21 | D7: 21 | E7: 21 | F7: 21 | G7: 21 | H7: 21 | I7: 21 | J7: 15 | K7: 17 | L7: 21 | M7: 21
A8: 日平均利用者数 | B8: =B5*B6 -> 2.4 | C8: =C5*C6 -> 4 | D8: =D5*D6 -> 5.6 | E8: =E5*E6 -> 7.2 | F8: =F5*F6 -> 8 | G8: =G5*G6 -> 8.8 | H8: =H5*H6 -> 9.6 | I8: =I5*I6 -> 10.4 | ... M8: =M5*M6 -> 12
A9: 稼働率(参考) | B9: =B8/前提条件!$B$3 -> 0.12 | C9: =C8/前提条件!$B$3 -> 0.2 | D9: =D8/前提条件!$B$3 -> 0.28 | E9: =E8/前提条件!$B$3 -> 0.36 | F9: =F8/前提条件!$B$3 -> 0.4 | G9: =G8/前提条件!$B$3 -> 0.44 | H9: =H8/前提条件!$B$3 -> 0.48 | I9: =I8/前提条件!$B$3 -> 0.52 | ... M9: =M8/前提条件!$B$3 -> 0.6
A10: 1人1日あたり収入(基本+送迎+処遇改善) | B10: =前提条件!$B$5*前提条件!$B$9+前提条件!$B$13*(前提条件!$B$10+前提条件!$B$12*前提条件!$B$11)*前提条件!$B$9+前提条件!$B$5*前提条件!$B$9*前提条件!$B$14 -> 11438.057 | C10: =前提条件!$B$5*前提条件!$B$9+前提条件!$B$13*(前提条件!$B$10+前提条件!$B$12*前提条件!$B$11)*前提条件!$B$9+前提条件!$B$5*前提条件!$B$9*前提条件!$B$14 -> 11438.057 | D10: =前提条件!$B$5*前提条件!$B$9+前提条件!$B$13*(前提条件!$B$10+前提条件!$B$12*前提条件!$B$11)*前提条件!$B$9+前提条件!$B$5*前提条件!$B$9*前提条件!$B$14 -> 11438.057 | E10: =前提条件!$B$5*前提条件!$B$9+前提条件!$B$13*(前提条件!$B$10+前提条件!$B$12*前提条件!$B$11)*前提条件!$B$9+前提条件!$B$5*前提条件!$B$9*前提条件!$B$14 -> 11438.057 | F10: =前提条件!$B$5*前提条件!$B$9+前提条件!$B$13*(前提条件!$B$10+前提条件!$B$12*前提条件!$B$11)*前提条件!$B$9+前提条件!$B$5*前提条件!$B$9*前提条件!$B$14 -> 11438.057 | G10: =前提条件!$B$5*前提条件!$B$9+前提条件!$B$13*(前提条件!$B$10+前提条件!$B$12*前提条件!$B$11)*前提条件!$B$9+前提条件!$B$5*前提条件!$B$9*前提条件!$B$14 -> 11438.057 | H10: =前提条件!$B$5*前提条件!$B$9+前提条件!$B$13*(前提条件!$B$10+前提条件!$B$12*前提条件!$B$11)*前提条件!$B$9+前提条件!$B$5*前提条件!$B$9*前提条件!$B$14 -> 11438.057 | I10: =前提条件!$B$5*前提条件!$B$9+前提条件!$B$13*(前提条件!$B$10+前提条件!$B$12*前提条件!$B$11)*前提条件!$B$9+前提条件!$B$5*前提条件!$B$9*前提条件!$B$14 -> 11438.057 | ... M10: =前提条件!$B$5*前提条件!$B$9+前提条件!$B$13*(前提条件!$B$10+前提条件!$B$12*前提条件!$B$11)*前提条件!$B$9+前提条件!$B$5*前提条件!$B$9*前提条件!$B$14 -> 11438.057
A11: 当月発生収入(サービス提供分) | B11: =B8*B10*B7 -> 576478.06 | C11: =C8*C10*C7 -> 960796.77 | D11: =D8*D10*D7 -> 1345115.5 | E11: =E8*E10*E7 -> 1729434.2 | F11: =F8*F10*F7 -> 1921593.5 | G11: =G8*G10*G7 -> 2113752.9 | H11: =H8*H10*H7 -> 2305912.3 | I11: =I8*I10*I7 -> 2498071.6 | ... M11: =M8*M10*M7 -> 2882390.3
A12: 当月入金(翌々月ラグ反映) | B12: 0 | C12: 0 | D12: =B11 -> 576478.06 | E12: =C11 -> 960796.77 | F12: =D11 -> 1345115.5 | G12: =E11 -> 1729434.2 | H12: =F11 -> 1921593.5 | I12: =G11 -> 2113752.9 | J12: =H11 -> 2305912.3 | K12: =I11 -> 2498071.6 | ... M12: =K11 -> 2177806
A13: 当月支出(人件費/12＋家賃＋その他経費/12＋車両費/12) | B13: =人件費!$D$12/12+前提条件!$B$22+前提条件!$B$24/12+前提条件!$B$23/12 -> 4166833.3 | C13: =人件費!$D$12/12+前提条件!$B$22+前提条件!$B$24/12+前提条件!$B$23/12 -> 4166833.3 | D13: =人件費!$D$12/12+前提条件!$B$22+前提条件!$B$24/12+前提条件!$B$23/12 -> 4166833.3 | E13: =人件費!$D$12/12+前提条件!$B$22+前提条件!$B$24/12+前提条件!$B$23/12 -> 4166833.3 | F13: =人件費!$D$12/12+前提条件!$B$22+前提条件!$B$24/12+前提条件!$B$23/12 -> 4166833.3 | G13: =人件費!$D$12/12+前提条件!$B$22+前提条件!$B$24/12+前提条件!$B$23/12 -> 4166833.3 | H13: =人件費!$D$12/12+前提条件!$B$22+前提条件!$B$24/12+前提条件!$B$23/12 -> 4166833.3 | I13: =人件費!$D$12/12+前提条件!$B$22+前提条件!$B$24/12+前提条件!$B$23/12 -> 4166833.3 | ... M13: =人件費!$D$12/12+前提条件!$B$22+前提条件!$B$24/12+前提条件!$B$23/12 -> 4166833.3
A14: 単月収支(入金－支出) | B14: =B12-B13 -> -4166833.3 | C14: =C12-C13 -> -4166833.3 | D14: =D12-D13 -> -3590355.3 | E14: =E12-E13 -> -3206036.6 | F14: =F12-F13 -> -2821717.9 | G14: =G12-G13 -> -2437399.1 | H14: =H12-H13 -> -2245239.8 | I14: =I12-I13 -> -2053080.4 | ... M14: =M12-M13 -> -1989027.3
A15: 累積収支(運転資金投入前) | B15: =B14 -> -4166833.3 | C15: =B15+C14 -> -8333666.7 | D15: =C15+D14 -> -11924022 | E15: =D15+E14 -> -15130058 | F15: =E15+F14 -> -17951776 | G15: =F15+G14 -> -20389175 | H15: =G15+H14 -> -22634415 | I15: =H15+I14 -> -24687496 | J15: =I15+J14 -> -26548417 | ... M15: =L15+M14 -> -32588702
A17: Year1中の最低累積収支(＝最低限必要な開所前資金の目安) | B17: =MIN(B15:M15) -> -32588702 | C17: ←この金額の絶対値以上を、開所前に確保しておく必要がある(初期投資シートの『運転資金』はこの値を参照)

Sheet 収支計画5年
A1: 5ヵ年収支計画(概算シミュレーション)
A2: 項目 | B2: Year1 | C2: Year2 | D2: Year3 | E2: Year4 | F2: Year5
A3: 稼働率(想定・入力。Year1は月次資金繰りシートの積み上げ平均目安) | B3: 0.35 | C3: 0.65 | D3: 0.8 | E3: 0.85 | F3: 0.85
A4: 平均利用者数/日(人) | B4: =前提条件!$B$3*B3 -> 7 | C4: =前提条件!$B$3*C3 -> 13 | D4: =前提条件!$B$3*D3 -> 16 | E4: =前提条件!$B$3*E3 -> 17 | F4: =前提条件!$B$3*F3 -> 17
A5: 年間開所日数(日) | B5: =前提条件!$B$21 -> 250 | C5: =前提条件!$B$21 -> 250 | D5: =前提条件!$B$21 -> 250 | E5: =前提条件!$B$21 -> 250 | F5: =前提条件!$B$21 -> 250
A6: 基本報酬単価(円/日/人) | B6: =前提条件!$B$5*前提条件!$B$9 -> 10170.2 | C6: =前提条件!$B$5*前提条件!$B$9 -> 10170.2 | D6: =前提条件!$B$5*前提条件!$B$9 -> 10170.2 | E6: =前提条件!$B$5*前提条件!$B$9 -> 10170.2 | F6: =前提条件!$B$5*前提条件!$B$9 -> 10170.2
A7: 人員配置体制加算Ⅲ 採用フラグ(0=不採用/1=採用。「理念優先」の経営方針決定を受け、Year3以降で正式採用を推奨。Year1-2は追加人件費が加算収入を上回るため見送り推奨) | B7: 0 | C7: 0 | D7: 1 | E7: 1 | F7: 1
A9: 【収入】
A10: 基本報酬収入 | B10: =B4*B6*B5 -> 17797850 | C10: =C4*C6*C5 -> 33053150 | D10: =D4*D6*D5 -> 40680800 | E10: =E4*E6*E5 -> 43223350 | F10: =F4*F6*F5 -> 43223350
A11: 送迎加算収入(基本21単位＋区分5/6要件充足時+28単位、往復) | B11: =B4*前提条件!$B$13*((前提条件!$B$10+前提条件!$B$12*前提条件!$B$11)*2)*前提条件!$B$9*B5 -> 1447460 | C11: =C4*前提条件!$B$13*((前提条件!$B$10+前提条件!$B$12*前提条件!$B$11)*2)*前提条件!$B$9*C5 -> 2688140 | D11: =D4*前提条件!$B$13*((前提条件!$B$10+前提条件!$B$12*前提条件!$B$11)*2)*前提条件!$B$9*D5 -> 3308480 | E11: =E4*前提条件!$B$13*((前提条件!$B$10+前提条件!$B$12*前提条件!$B$11)*2)*前提条件!$B$9*E5 -> 3515260 | F11: =F4*前提条件!$B$13*((前提条件!$B$10+前提条件!$B$12*前提条件!$B$11)*2)*前提条件!$B$9*F5 -> 3515260
A12: 処遇改善加算収入(全額を人件費側の賃金改善原資に充当。損益には中立) | B12: =B10*前提条件!$B$14 -> 1495019.4 | C12: =C10*前提条件!$B$14 -> 2776464.6 | D12: =D10*前提条件!$B$14 -> 3417187.2 | E12: =E10*前提条件!$B$14 -> 3630761.4 | F12: =F10*前提条件!$B$14 -> 3630761.4
A13: 入浴介助加算収入 | B13: =B4*前提条件!$B$16*前提条件!$B$17*(前提条件!$B$21/5)*前提条件!$B$18*前提条件!$B$9 -> 147700 | C13: =C4*前提条件!$B$16*前提条件!$B$17*(前提条件!$B$21/5)*前提条件!$B$18*前提条件!$B$9 -> 274300 | D13: =D4*前提条件!$B$16*前提条件!$B$17*(前提条件!$B$21/5)*前提条件!$B$18*前提条件!$B$9 -> 337600 | E13: =E4*前提条件!$B$16*前提条件!$B$17*(前提条件!$B$21/5)*前提条件!$B$18*前提条件!$B$9 -> 358700 | F13: =F4*前提条件!$B$16*前提条件!$B$17*(前提条件!$B$21/5)*前提条件!$B$18*前提条件!$B$9 -> 358700
A14: 食事提供体制加算収入(経過措置) | B14: =B4*前提条件!$B$19*前提条件!$B$20*前提条件!$B$9*B5 -> 166162.5 | C14: =C4*前提条件!$B$19*前提条件!$B$20*前提条件!$B$9*C5 -> 308587.5 | D14: =D4*前提条件!$B$19*前提条件!$B$20*前提条件!$B$9*D5 -> 379800 | E14: =E4*前提条件!$B$19*前提条件!$B$20*前提条件!$B$9*E5 -> 403537.5 | F14: =F4*前提条件!$B$19*前提条件!$B$20*前提条件!$B$9*F5 -> 403537.5
A15: 福祉専門職員配置等加算収入(有資格者比率要件、追加人件費なしで取得可) | B15: =B4*前提条件!$B$15*前提条件!$B$9*B5 -> 387712.5 | C15: =C4*前提条件!$B$15*前提条件!$B$9*C5 -> 720037.5 | D15: =D4*前提条件!$B$15*前提条件!$B$9*D5 -> 886200 | E15: =E4*前提条件!$B$15*前提条件!$B$9*E5 -> 941587.5 | F15: =F4*前提条件!$B$15*前提条件!$B$9*F5 -> 941587.5
A16: 人員配置体制加算Ⅲ収入(理念優先方針により正式採用。上記フラグに連動) | B16: =B4*B7*加算フル活用シナリオ!$B$12*前提条件!$B$9*B5 -> 0 | C16: =C4*C7*加算フル活用シナリオ!$B$12*前提条件!$B$9*C5 -> 0 | D16: =D4*D7*加算フル活用シナリオ!$B$12*前提条件!$B$9*D5 -> 7638200 | E16: =E4*E7*加算フル活用シナリオ!$B$12*前提条件!$B$9*E5 -> 8115587.5 | F16: =F4*F7*加算フル活用シナリオ!$B$12*前提条件!$B$9*F5 -> 8115587.5
A17: 収入合計 | B17: =SUM(B10:B16) -> 21441904 | C17: =SUM(C10:C16) -> 39820680 | D17: =SUM(D10:D16) -> 56648267 | E17: =SUM(E10:E16) -> 60188784 | F17: =SUM(F10:F16) -> 60188784
A19: 【経費】
A20: 人件費(法定福利費込、看護・機能訓練指導員含む) | B20: =人件費!$D$12 -> 39652000 | C20: =人件費!$D$12 -> 39652000 | D20: =人件費!$D$12 -> 39652000 | E20: =人件費!$D$12 -> 39652000 | F20: =人件費!$D$12 -> 39652000
A21: 処遇改善加算 相当額の賃金改善(加算収入と同額、損益中立化) | B21: =B12 -> 1495019.4 | C21: =C12 -> 2776464.6 | D21: =D12 -> 3417187.2 | E21: =E12 -> 3630761.4 | F21: =F12 -> 3630761.4
A22: 豊口氏 役員報酬(Year1-2は月10万円、Year3以降は月30万円を想定) | B22: 1200000 | C22: 1200000 | D22: 3600000 | E22: 3600000 | F22: 3600000
A23: 地代家賃 | B23: =前提条件!$B$22*12 -> 4800000 | C23: =前提条件!$B$22*12 -> 4800000 | D23: =前提条件!$B$22*12 -> 4800000 | E23: =前提条件!$B$22*12 -> 4800000 | F23: =前提条件!$B$22*12 -> 4800000
A24: 車両関連費 | B24: =前提条件!$B$23 -> 900000 | C24: =前提条件!$B$23 -> 900000 | D24: =前提条件!$B$23 -> 900000 | E24: =前提条件!$B$23 -> 900000 | F24: =前提条件!$B$23 -> 900000
A25: その他経費 | B25: =前提条件!$B$24 -> 4650000 | C25: =前提条件!$B$24 -> 4650000 | D25: =前提条件!$B$24 -> 4650000 | E25: =前提条件!$B$24 -> 4650000 | F25: =前提条件!$B$24 -> 4650000
A26: 減価償却費 | B26: =前提条件!$B$25/前提条件!$B$26 -> 2312500 | C26: =前提条件!$B$25/前提条件!$B$26 -> 2312500 | D26: =前提条件!$B$25/前提条件!$B$26 -> 2312500 | E26: =前提条件!$B$25/前提条件!$B$26 -> 2312500 | F26: =前提条件!$B$25/前提条件!$B$26 -> 2312500
A27: 人員配置体制加算Ⅲ対応 追加人件費(生活支援員+1.5名相当、法定福利費込。上記フラグに連動) | B27: =B7*加算フル活用シナリオ!$C$12*加算フル活用シナリオ!$B$8 -> 0 | C27: =C7*加算フル活用シナリオ!$C$12*加算フル活用シナリオ!$B$8 -> 0 | D27: =D7*加算フル活用シナリオ!$C$12*加算フル活用シナリオ!$B$8 -> 6210000 | E27: =E7*加算フル活用シナリオ!$C$12*加算フル活用シナリオ!$B$8 -> 6210000 | F27: =F7*加算フル活用シナリオ!$C$12*加算フル活用シナリオ!$B$8 -> 6210000
A28: 経費合計 | B28: =SUM(B20:B27) -> 55009519 | C28: =SUM(C20:C27) -> 56290965 | D28: =SUM(D20:D27) -> 65541687 | E28: =SUM(E20:E27) -> 65755261 | F28: =SUM(F20:F27) -> 65755261
A30: 営業利益 | B30: =B17-B28 -> -33567615 | C30: =C17-C28 -> -16470285 | D30: =D17-D28 -> -8893420 | E30: =E17-E28 -> -5566477.5 | F30: =F17-F28 -> -5566477.5
A31: 営業利益率 | B31: =IFERROR(B30/B17,0) -> -1.5655146 | C31: =IFERROR(C30/C17,0) -> -0.41361135 | D31: =IFERROR(D30/D17,0) -> -0.15699368 | E31: =IFERROR(E30/E17,0) -> -0.092483635 | F31: =IFERROR(F30/F17,0) -> -0.092483635
A33: 【簡易資金繰り(参考)】
A34: 簡易キャッシュフロー(営業利益+減価償却費) | B34: =B30+B26 -> -31255115 | C34: =C30+C26 -> -14157785 | D34: =D30+D26 -> -6580920 | E34: =E30+E26 -> -3253977.5 | F34: =F30+F26 -> -3253977.5
A35: 融資元金返済(公庫＋会長、想定・入力) | B35: 0 | C35: 3500000 | D35: 4000000 | E35: 4000000 | F35: 4000000
A36: 単年キャッシュフロー | B36: =B34-B35 -> -31255115 | C36: =C34-C35 -> -17657785 | D36: =D34-D35 -> -10580920 | E36: =E34-E35 -> -7253977.5 | F36: =F34-F35 -> -7253977.5
A37: 累積キャッシュフロー(開所後・初期投資の運転資金充当分は除く) | B37: =B36 -> -31255115 | C37: =B37+C36 -> -48912900 | D37: =C37+D36 -> -59493820 | E37: =D37+E36 -> -66747798 | F37: =E37+F36 -> -74001775

Sheet 加算フル活用シナリオ
A1: 加算フル活用シナリオ ― 人員配置体制加算・重度障害者支援加算の損益分岐試算
A2: 「収支計画5年」の基本ケースには、追加人件費なしで取得を狙える加算(食事提供体制加算・入浴支援加算・送迎加算・処遇改善加算フル取得・福祉専門職員配置等加算)のみを織り込んでいる。人員配置体制加算(追加人員が必要)と重度障害者支援加算(該当者の受け入れが前提)は、コスト・前提条件が別次元のため、本シートで独立に損益分岐を試算する。単位数・要件は公表情報からの概算であり、広島市提示の最新単価表・算定要件で必ず確認すること(青字セルは入力用)。
A4: 【試算の前提(Year5・成熟期時点)】
A5: 想定利用者数/日(Year5) | B5: =収支計画5年!$F$4 -> 17 | C5: 人
A6: 年間開所日数 | B6: =前提条件!$B$21 -> 250 | C6: 日
A7: 単位単価 | B7: =前提条件!$B$9 -> 10.55 | C7: 円/単位
A8: 生活支援員 年間人件費単価(法定福利費込) | B8: =人件費!$C$5*1.15 -> 4140000 | C8: 円/人
A10: 【① 人員配置体制加算(生活支援員の増員が必要)】
A11: 区分(定員20人以下の目安) | B11: 単位数(要確認) | C11: 追加で必要な生活支援員数(想定・入力) | D11: 追加人件費(年) | E11: 追加収入(年) | F11: 差引効果(年)
A12: Ⅲ(概ね2:1程度と推定) | B12: 181 | C12: 1.5 | D12: =C12*$B$8 -> 6210000 | E12: =$B$5*B12*$B$7*$B$6 -> 8115587.5 | F12: =E12-D12 -> 1905587.5
A13: Ⅱ(概ね1.75:1程度と推定) | B13: 265 | C13: 3 | D13: =C13*$B$8 -> 12420000 | E13: =$B$5*B13*$B$7*$B$6 -> 11881938 | F13: =E13-D13 -> -538062.5
A14: Ⅰ(概ね1.5:1程度と推定、321単位) | B14: 321 | C14: 5.9 | D14: =C14*$B$8 -> 24426000 | E14: =$B$5*B14*$B$7*$B$6 -> 14392838 | F14: =E14-D14 -> -10033162
A16: ※配置比率と区分(Ⅰ〜Ⅳ)の対応、および「追加で必要な生活支援員数」は現行7.4名体制からの概算推定であり、正確な要件は広島市の単価表で必ず確認すること。差引効果がプラスであれば取得を検討する価値が高い。【経営方針決定(理念優先)を反映】Ⅲは「収支計画5年」シートに正式採用として反映済み。ただし追加人件費(約621万円/年)は稼働率が上がるYear1から必要になる一方、収入は利用者数に比例して低いため、Year1適用だと収支をさらに悪化させる(下記の年次試算を参照)。そこで「収支計画5年」シートでは、差引効果がプラスに転じるYear3以降でのみ適用する「採用フラグ」を設け、Year1-2は見送る設計とした。Ⅱ・Ⅰは現在の人件費水準では通期で不採算のため不採用。
A18: 【人員配置体制加算Ⅲ 年次試算(理念優先方針の判断根拠。「収支計画5年」シートの採用フラグと連動)】
A19: 項目 | B19: Year1 | C19: Year2 | D19: Year3 | E19: Year4 | F19: Year5
A20: 想定利用者数/日(人) | B20: =収支計画5年!B$4 -> 7 | C20: =収支計画5年!C$4 -> 13 | D20: =収支計画5年!D$4 -> 16 | E20: =収支計画5年!E$4 -> 17 | F20: =収支計画5年!F$4 -> 17
A21: 追加人件費(年、想定通年ベース) | B21: =$C$12*$B$8 -> 6210000 | C21: =$C$12*$B$8 -> 6210000 | D21: =$C$12*$B$8 -> 6210000 | E21: =$C$12*$B$8 -> 6210000 | F21: =$C$12*$B$8 -> 6210000
A22: 追加収入(年) | B22: =B20*$B$12*$B$7*$B$6 -> 3341712.5 | C22: =C20*$B$12*$B$7*$B$6 -> 6206037.5 | D22: =D20*$B$12*$B$7*$B$6 -> 7638200 | E22: =E20*$B$12*$B$7*$B$6 -> 8115587.5 | F22: =F20*$B$12*$B$7*$B$6 -> 8115587.5
A23: 差引効果(年、フラグ適用前の仮採用ベース) | B23: =B22-B21 -> -2868287.5 | C23: =C22-C21 -> -3962.5 | D23: =D22-D21 -> 1428200 | E23: =E22-E21 -> 1905587.5 | F23: =F22-F21 -> 1905587.5
A24: 採用フラグ(実際に「収支計画5年」で適用するか) | B24: =収支計画5年!B$7 -> 0 | C24: =収支計画5年!C$7 -> 0 | D24: =収支計画5年!D$7 -> 1 | E24: =収支計画5年!E$7 -> 1 | F24: =収支計画5年!F$7 -> 1
A26: ※差引効果はYear1・Year2でマイナス(追加人件費が追加収入を上回る)、Year3で黒字転換する。これが「収支計画5年」シートの採用フラグをYear1-2=0、Year3以降=1に設定した根拠。Year1から通年で加算Ⅲを採用すると、資金繰りが最も厳しい開設初年度の赤字をさらに拡大させてしまうため。
A28: 【② 重度障害者支援加算(該当者の受け入れが前提。追加人件費は原則不要)】
A29: 区分 | B29: 単位数(要確認) | C29: 該当者数(想定・入力) | D29: 追加人件費(年、概算) | E29: 追加収入(年) | F29: 差引効果(年)
A30: Ⅲ(区分6かつ行動関連項目10点以上) | B30: 180 | C30: 3 | D30: 0 | E30: =C30*B30*$B$7*$B$6 -> 1424250 | F30: =E30-D30 -> 1424250
A32: ※要件：生活支援員の20%以上が強度行動障害支援者養成研修(基礎研修)修了者であること、サービス管理責任者又は生活支援員1名以上が実践研修修了者であること(丸山氏または生活支援員の研修受講で対応可、追加人件費は原則不要と想定)。該当者数は「区分6かつ行動関連項目10点以上」の利用者の受け入れ見込みであり、営業活動(第4章)の結果次第で変動する。加算算定開始から180日以内はさらに上乗せがある制度になっているため、実際にはこれより上振れる可能性がある。
